sqlfmt/__init__.py
sqlfmt/__main__.py
sqlfmt/actions.py
sqlfmt/analyzer.py
sqlfmt/api.py
sqlfmt/cache.py
sqlfmt/cli.py
sqlfmt/comment.py
sqlfmt/config.py
sqlfmt/dialect.py
sqlfmt/exception.py
sqlfmt/jinjafmt.py
sqlfmt/line.py
sqlfmt/merger.py
sqlfmt/mode.py
sqlfmt/node.py
sqlfmt/node_manager.py
sqlfmt/operator_precedence.py
sqlfmt/py.typed
sqlfmt/query.py
sqlfmt/query_formatter.py
sqlfmt/report.py
sqlfmt/rule.py
sqlfmt/segment.py
sqlfmt/splitter.py
sqlfmt/tokens.py
sqlfmt/rules/__init__.py
sqlfmt/rules/clone.py
sqlfmt/rules/common.py
sqlfmt/rules/core.py
sqlfmt/rules/function.py
sqlfmt/rules/grant.py
sqlfmt/rules/jinja.py
sqlfmt/rules/pragma.py
sqlfmt/rules/unsupported.py
sqlfmt/rules/warehouse.py
shandy_sqlfmt-0.28.1.dist-info/METADATA
shandy_sqlfmt-0.28.1.dist-info/WHEEL
shandy_sqlfmt-0.28.1.dist-info/entry_points.txt
shandy_sqlfmt-0.28.1.dist-info/licenses/LICENSE
shandy_sqlfmt-0.28.1.dist-info/RECORD
