Metadata-Version: 2.4
Name: shandy-sqlfmt
Version: 0.28.1
Summary: sqlfmt formats your dbt SQL files so you don't have to.
Project-URL: Homepage, https://sqlfmt.com
Project-URL: Repository, https://github.com/tconbeer/sqlfmt
Project-URL: Documentation, https://docs.sqlfmt.com
Project-URL: Bug Tracker, https://github.com/tconbeer/sqlfmt/issues
Project-URL: Changelog, https://github.com/tconbeer/sqlfmt/blob/main/CHANGELOG.md
Author-email: Ted Conbeer <tconbeer@users.noreply.github.com>
License-Expression: Apache-2.0
License-File: LICENSE
Classifier: Operating System :: MacOS :: MacOS X
Classifier: Operating System :: Microsoft :: Windows
Classifier: Operating System :: POSIX :: Linux
Classifier: Programming Language :: SQL
Classifier: Topic :: Software Development :: Quality Assurance
Classifier: Typing :: Typed
Requires-Python: <3.15,>=3.8
Requires-Dist: click<8.2,>=8.1
Requires-Dist: importlib-metadata<9,>=8.0; python_version < '3.10'
Requires-Dist: jinja2<4,>=3.0
Requires-Dist: platformdirs<5.0,>=2.4
Requires-Dist: tomli<3,>=2.0; python_version < '3.11'
Requires-Dist: tqdm<5,>=4.67
Provides-Extra: jinjafmt
Requires-Dist: black>=24; extra == 'jinjafmt'
